houdini_logging_tools/__init__.py
houdini_logging_tools/mappings.py
houdini_logging_tools/adapters/__init__.py
houdini_logging_tools/adapters/loggeradapter.py
houdini_logging_tools/handlers/__init__.py
houdini_logging_tools/handlers/houdini_logging.py
houdini_logging_tools/handlers/shellio.py
houdini_logging_tools-0.2.0.dist-info/licenses/LICENSE
houdini_logging_tools-0.2.0.dist-info/METADATA
houdini_logging_tools-0.2.0.dist-info/WHEEL
houdini_logging_tools-0.2.0.dist-info/top_level.txt
houdini_logging_tools-0.2.0.dist-info/RECORD
